unit_analysis/__init__.py
unit_analysis/unit.py
unit_analysis_package-1.0.2.dist-info/METADATA
unit_analysis_package-1.0.2.dist-info/WHEEL
unit_analysis_package-1.0.2.dist-info/RECORD
