Metadata-Version: 2.4
Name: unit-analysis-package
Version: 1.0.2
Summary: A powerful class for physical unit and dimensional analysis in engineering applications.
Project-URL: Homepage, https://github.com/Abstergo2003/Miscellaneous/tree/main/PyUnit
Project-URL: Documentation, https://github.com/Abstergo2003/Miscellaneous/tree/main/PyUnit%23readme
Project-URL: Issues, https://github.com/Abstergo2003/Miscellaneous/tree/main/PyUnit/issues
Author-email: Abstergo## <abstergo.hash@gmail.com>
License: Apache-2.0
Keywords: dimensional-analysis,engineering,metric,physics,units
Classifier: Development Status :: 4 - Beta
Classifier: Intended Audience :: Developers
Classifier: Intended Audience :: Education
Classifier: Intended Audience :: Science/Research
Classifier: License :: OSI Approved :: Apache Software License
Classifier: Programming Language :: Python :: 3
Classifier: Programming Language :: Python :: 3.8
Classifier: Programming Language :: Python :: 3.9
Classifier: Programming Language :: Python :: 3.10
Classifier: Programming Language :: Python :: 3.11
Classifier: Programming Language :: Python :: 3.12
Classifier: Topic :: Scientific/Engineering
Classifier: Topic :: Software Development :: Libraries :: Python Modules
Requires-Python: >=3.8
